{
  "id": 178891,
  "uri": "https://dadosabertos.camara.leg.br/api/v2/deputados/178891",
  "nomeCivil": "CAIO NARCIO RODRIGUES DA SILVEIRA",
  "ultimoStatus": {
    "id": 178891,
    "uri": "https://dadosabertos.camara.leg.br/api/v2/deputados/178891",
    "nome": "CAIO NARCIO",
    "siglaPartido": "PSDB",
    "uriPartido": "https://dadosabertos.camara.leg.br/api/v2/partidos/36835",
    "siglaUf": "MG",
    "idLegislatura": 55,
    "urlFoto": "http://www.camara.leg.br/internet/deputado/bandep/178891.jpg",
    "data": "2015-02-01",
    "nomeEleitoral": "CAIO NARCIO",
    "gabinete": {
      "nome": "431",
      "predio": "4",
      "sala": "431",
      "andar": "4",
      "telefone": "3215-5431",
      "email": "dep.caionarcio@camara.leg.br"
    },
    "situacao": "Exercício",
    "condicaoEleitoral": "Titular",
    "descricaoStatus": null
  },
  "cpf": "",
  "sexo": "M",
  "urlWebsite": null,
  "redeSocial": [
    "Facebook/CaioNarcio"
  ],
  "dataNascimento": "1986-08-21",
  "dataFalecimento": null,
  "ufNascimento": "MG",
  "municipioNascimento": "Uberlândia",
  "escolaridade": "Superior"
}