{
  "id": 73692,
  "uri": "https://dadosabertos.camara.leg.br/api/v2/deputados/73692",
  "nomeCivil": "OSMAR GASPARINI TERRA",
  "ultimoStatus": {
    "id": 73692,
    "uri": "https://dadosabertos.camara.leg.br/api/v2/deputados/73692",
    "nome": "OSMAR TERRA",
    "siglaPartido": "PMDB",
    "uriPartido": "https://dadosabertos.camara.leg.br/api/v2/partidos/36800",
    "siglaUf": "RS",
    "idLegislatura": 55,
    "urlFoto": "http://www.camara.leg.br/internet/deputado/bandep/73692.jpg",
    "data": "2015-02-01",
    "nomeEleitoral": "OSMAR TERRA",
    "gabinete": {
      "nome": "927",
      "predio": "4",
      "sala": "927",
      "andar": "9",
      "telefone": "3215-5927",
      "email": "dep.osmarterra@camara.leg.br"
    },
    "situacao": "Exercício",
    "condicaoEleitoral": "Titular",
    "descricaoStatus": null
  },
  "cpf": "",
  "sexo": "M",
  "urlWebsite": null,
  "redeSocial": [],
  "dataNascimento": "1950-02-18",
  "dataFalecimento": null,
  "ufNascimento": "RS",
  "municipioNascimento": "Porto Alegre",
  "escolaridade": null
}